codeinsight/__init__.py
codeinsight/analyzer.py
codeinsight/cli.py
codeinsight-1.0.1.dist-info/METADATA
codeinsight-1.0.1.dist-info/WHEEL
codeinsight-1.0.1.dist-info/entry_points.txt
codeinsight-1.0.1.dist-info/top_level.txt
codeinsight-1.0.1.dist-info/RECORD
