Metadata-Version: 2.2
Name: codeinsight
Version: 1.0.1
Summary: Live time complexity and memory usage analysis for Python code
Home-page: https://github.com/Azad11014/codeanalyzer
Author: Azad
Author-email: azad1.dev0@gmail.com
License: MIT
Project-URL: Documentation, https://github.com/Azad11014/codeinsight
Keywords: code analysis,complexity,performance,metrics,quality
Requires-Python: >=3.6
Requires-Dist: radon
Requires-Dist: memory_profiler
Requires-Dist: astor
Requires-Dist: numpy
Requires-Dist: rich
Requires-Dist: click
Dynamic: author
Dynamic: author-email
Dynamic: description
Dynamic: description-content-type
Dynamic: home-page
Dynamic: keywords
Dynamic: license
Dynamic: project-url
Dynamic: requires-dist
Dynamic: requires-python
Dynamic: summary
